{"pic_name": "pic_ea365220a5fe0ccd678cfd7d6e6cd76be260f6e9.png", "width": 590, "height": 207, "fragment": [{"box": [26, 41, 509, 139], "rotate_box": [[218, 107], [219, 72], [314, 73], [313, 109]], "char_boxes": [[[220, 61], [243, 63], [238, 111], [215, 108]], [[245, 64], [255, 65], [251, 103], [241, 102]], [[256, 65], [276, 67], [272, 105], [252, 103]], [[278, 67], [298, 69], [294, 108], [274, 106]], [[300, 69], [319, 71], [315, 110], [296, 108]]], "data": "given", "orientation": "horizontal", "type": "TextBlock", "fragment_name": "fragment_ea365220a5fe0ccd678cfd7d6e6cd76be260f6e90.png"}, {"box": [26, 160, 308, 194], "rotate_box": [[113, 170], [219, 168], [220, 188], [114, 191]], "char_boxes": [[[112, 163], [128, 163], [129, 191], [113, 191]], [[130, 163], [148, 163], [149, 190], [131, 190]], [[150, 163], [166, 162], [167, 189], [151, 190]], [[168, 162], [183, 162], [184, 189], [169, 189]], [[185, 162], [202, 162], [203, 190], [186, 190]], [[204, 162], [220, 162], [221, 190], [205, 190]]], "data": "stocks", "orientation": "horizontal", "type": "TextBlock", "fragment_name": "fragment_ea365220a5fe0ccd678cfd7d6e6cd76be260f6e91.png"}]}